{
  "id": "supported_games",
  "title": "Supported Games",
  "description": "Many games supported by ScummVM can still be bought, and many others have been released for free download by their copyright holders. Most games have demo versions to try out which also run with ScummVM. These can be downloaded from the ScummVM demos page",
  "source": "@site/docs/supported_games.md",
  "permalink": "/supported_games",
  "editUrl": "https://github.com/ScummDocs/docs/supported_games.md",
  "sidebar_label": "Supported Games",
  "sidebar": "someSidebar",
  "previous": {
    "title": "How Does ScummVM Work?",
    "permalink": "/how_work"
  },
  "next": {
    "title": "Supported Platforms",
    "permalink": "/supported_platforms"
  }
}